sample/__init__.py
sample/kotifpg.py
koreanforpygame-0.1.dist-info/METADATA
koreanforpygame-0.1.dist-info/WHEEL
koreanforpygame-0.1.dist-info/top_level.txt
koreanforpygame-0.1.dist-info/RECORD
