Metadata-Version: 2.1
Name: koreanforpygame
Version: 0.1
Summary: Korean text input for pygame
Home-page: https://github.com/jinotter3/ktifpg
Author: Seonghyun Jin
Author-email: jinotter@gmail.com
License: UNKNOWN
Keywords: korean,pygame,input
Platform: UNKNOWN
Classifier: Programming Language :: Python :: 2.7
Classifier: Programming Language :: Python :: 3
Classifier: Programming Language :: Python :: 3.2
Classifier: Programming Language :: Python :: 3.3
Classifier: Programming Language :: Python :: 3.4
Classifier: Programming Language :: Python :: 3.5
Classifier: Programming Language :: Python :: 3.6
Classifier: Programming Language :: Python :: 3.6
Requires-Python: >=2
Requires-Dist: hgtk
